{"namespace":"anvil","water_recipe_grid@anvil.recipe_grid":{"controls":[{"input_item_slot@anvil.anvil_item_slot":{"grid_position":[0,0],"$item_collection_name":"anvil_input_items","$focus_id_binding_type":"none","$focus_id":"anvil_input","$focus_override_right_binding_type":"none","$focus_override_right":"anvil_material","$button_ref":"common.water_auto_place"}},{"plus":{"type":"panel","grid_position":[1,0],"controls":[{"plus_sign_icon@anvil.plus_sign_icon":{}}]}},{"material_item_slot@anvil.anvil_item_slot":{"grid_position":[2,0],"$item_collection_name":"anvil_material_items","$focus_id_binding_type":"none","$focus_id":"anvil_material","$focus_override_left_binding_type":"none","$focus_override_left":"anvil_input","$focus_override_right_binding_type":"none","$focus_override_right":"anvil_result","$button_ref":"common.water_auto_place"}},{"yields":{"type":"panel","grid_position":[3,0],"controls":[{"arrow_icon@anvil.arrow_icon":{}},{"cross_out_icon@anvil.cross_out_icon":{"layer":1}}]}},{"result_item_slot@anvil.anvil_item_slot":{"grid_position":[4,0],"$item_collection_name":"anvil_result_items","$button_ref":"common.water_auto_place","$focus_id_binding_type":"none","$focus_id":"anvil_result","$focus_override_left_binding_type":"none","$focus_override_left":"anvil_material"}}]},"water_recipe_panel@anvil.recipe_panel":{"controls":[{"recipe_grid@anvil.water_recipe_grid":{}},{"cost_label_0@anvil.cost_label":{"color":"$anvil_cost_fail_text_color","bindings":[{"binding_name":"#cost_text","binding_name_override":"#text"},{"binding_name":"#cost_text_red","binding_name_override":"#visible"}]}},{"cost_label_1@anvil.cost_label":{"color":"$anvil_cost_success_text_color","bindings":[{"binding_name":"#cost_text","binding_name_override":"#text"},{"binding_name":"#cost_text_green","binding_name_override":"#visible"}]}}],"bindings":[{"binding_type":"view","source_control_name":"chest.hide_auto_place_control","source_property_name":"#toggle_state","target_property_name":"#visible"}]},"text_edit_control@common.text_edit_box":{"max_length":30000,"enabled_newline":true},"generic_label":{"color":"White","font_type":"$WaterFontType"},"title_label@anvil.generic_label":{"offset":[-18,-6],"anchor_from":"top_left","anchor_to":"top_left"},"anvil_icon":{"type":"image","anchor_from":"top_left","anchor_to":"top_left","texture":"textures/ui/anvil_icon","size":[25,25],"offset":[0,10],"layer":1},"anvil_addicon@common.container_3D":{"$container_id":9502720,"anchor_from":"top_left","anchor_to":"top_left","offset":[-5,-4],"ignored":"(not $use_container_icon)"},"top_half_panel":{"type":"panel","anchor_from":"top_left","anchor_to":"top_left","size":["100% - 14px","50% - 14px"],"offset":[7,7],"controls":[{"icon_and_text_panel@anvil.icon_and_text_panel":{}},{"icon@anvil_addicon":{}},{"recipe_panel@anvil.recipe_panel":{"bindings":[{"binding_type":"view","source_control_name":"chest.hide_auto_place_control","source_property_name":"(not #toggle_state)","target_property_name":"#visible"}]}},{"water_auto@anvil.water_recipe_panel":{}},{"extra_buttons@chest.water_drop_buttons":{"offset":[-40,6]}}]},"anvil_panel":{"type":"panel","controls":[{"container_gamepad_helpers@common.container_gamepad_helpers":{}},{"flying_item_renderer@common.flying_item_renderer":{"layer":8}},{"selected_item_details_factory@common.selected_item_details_factory":{}},{"item_lock_notification_factory@common.item_lock_notification_factory":{}},{"snow@snow.snow_panel":{"$snow_layer":-10}},{"root_panel@common.root_panel":{"layer":1,"controls":[{"common_panel@common.common_panel":{}},{"anvil_screen_inventory":{"type":"panel","layer":2,"controls":[{"top_half_panel@anvil.top_half_panel":{}},{"doll@chest.paper_doll":{"offset":[190,-14]}},{"inf@chest.inf":{"offset":[150,-46]}},{"auto_hotbar_grid@common.water_hotbar_grid_template":{}},{"auto_place@common.water_inventory_panel_bottom_half_with_label":{}},{"inventory_panel_bottom_half_with_label@common.inventory_panel_bottom_half_with_label":{}},{"hotbar_grid@common.hotbar_grid_template":{}},{"inventory_take_progress_icon_button@common.inventory_take_progress_icon_button":{}}]}},{"inventory_selected_icon_button@common.inventory_selected_icon_button":{}},{"gamepad_cursor@common.gamepad_cursor_button":{}}]}}]},"anvil_screen@common.inventory_screen_common":{"close_on_player_hurt":false,"$screen_content":"anvil.anvil_panel","$screen_bg_content":"common.screen_background","variables":[]}}